README.md
setup.py
pyaget_fucs/FUCClass.py
pyaget_fucs/__init__.py
pyaget_fucs/chatMessagesVersions.py
pyaget_fucs/fucsFiller.py
pyaget_fucs/onedriveSettings.py
pyaget_fucs/pyle.py
pyaget_fucs/sharePointAccess.py
pyaget_fucs.egg-info/PKG-INFO
pyaget_fucs.egg-info/SOURCES.txt
pyaget_fucs.egg-info/dependency_links.txt
pyaget_fucs.egg-info/requires.txt
pyaget_fucs.egg-info/top_level.txt