Metadata-Version: 2.1
Name: pyaget_fucs
Version: 1.1.0
Summary: Piaget's FUCs filler
Author: Natanael Quintino
Author-email: natanael.quintino@ipiaget.pt
License: CC0 1.0 Universal
Keywords: automation,curricular unit,FUC,piaget
Classifier: Intended Audience :: Developers
Classifier: Programming Language :: Python :: 3
Requires-Dist: pdflatex
Requires-Dist: langchain_openai
